qr_code_reader/QrCodeReader.py
qr_code_reader/__init__.py
qr_code_reader-1.1.5.dist-info/LICENSE
qr_code_reader-1.1.5.dist-info/METADATA
qr_code_reader-1.1.5.dist-info/WHEEL
qr_code_reader-1.1.5.dist-info/top_level.txt
qr_code_reader-1.1.5.dist-info/RECORD
